substrate/.keep
substrate/GEN_VERSION
substrate/__init__.py
substrate/_client.py
substrate/_version.py
substrate/core/__init__.py
substrate/core/_version.py
substrate/core/base_future.py
substrate/core/client/__init__.py
substrate/core/client/find_futures_client.py
substrate/core/client/future.py
substrate/core/client/graph.py
substrate/core/coregraph.py
substrate/core/corenode.py
substrate/core/future_directive.py
substrate/core/id_generator.py
substrate/core/models.py
substrate/core/node_ext/box.py
substrate/core/sb.py
substrate/future_dataclass_models.py
substrate/if_node.py
substrate/nodes.py
substrate/py.typed
substrate/run_python.py
substrate/streaming.py
substrate/substrate.py
substrate/substrate_response.py
substrate/typeddict_models.py
substrate-220240617.1.8.dist-info/LICENSE
substrate-220240617.1.8.dist-info/METADATA
substrate-220240617.1.8.dist-info/WHEEL
substrate-220240617.1.8.dist-info/RECORD
