Metadata-Version: 2.1
Name: substrate
Version: 220240617.1.8
Summary: Substrate Python SDK
Author: vprtwn
Author-email: ben@substrate.run
Requires-Python: >=3.9
Classifier: Programming Language :: Python :: 3
Classifier: Programming Language :: Python :: 3.9
Classifier: Programming Language :: Python :: 3.10
Classifier: Programming Language :: Python :: 3.11
Classifier: Programming Language :: Python :: 3.12
Requires-Dist: cloudpickle (==3.0.0)
Requires-Dist: distro (>=1.8.0)
Requires-Dist: httpx (>=0.26.0)
Requires-Dist: httpx-sse (>=0.4.0,<0.5.0)
Requires-Dist: networkx (>=3.2.1)
Requires-Dist: pydantic (>=1.0.0)
Requires-Dist: typing-extensions (>=4.10.0,<5.0.0)
